SpringBoot211ReleaseZhongwenWendang/README.md
SpringBoot211ReleaseZhongwenWendang/__init__.py
SpringBoot211ReleaseZhongwenWendang/__main__.py
SpringBoot211ReleaseZhongwenWendang/file.epub
SpringBoot211ReleaseZhongwenWendang/index.html
SpringBoot211ReleaseZhongwenWendang/css/__init__.py
SpringBoot211ReleaseZhongwenWendang/css/annotations.css
SpringBoot211ReleaseZhongwenWendang/css/main.css
SpringBoot211ReleaseZhongwenWendang/css/normalize.css
SpringBoot211ReleaseZhongwenWendang/css/popup.css
SpringBoot211ReleaseZhongwenWendang/font/__init__.py
SpringBoot211ReleaseZhongwenWendang/font/fontello.eot
SpringBoot211ReleaseZhongwenWendang/font/fontello.svg
SpringBoot211ReleaseZhongwenWendang/font/fontello.ttf
SpringBoot211ReleaseZhongwenWendang/font/fontello.woff
SpringBoot211ReleaseZhongwenWendang/img/__init__.py
SpringBoot211ReleaseZhongwenWendang/img/annotator-glyph-sprite.png
SpringBoot211ReleaseZhongwenWendang/img/annotator-icon-sprite.png
SpringBoot211ReleaseZhongwenWendang/img/apple-touch-icon.png
SpringBoot211ReleaseZhongwenWendang/img/cancelfullscreen.png
SpringBoot211ReleaseZhongwenWendang/img/close.png
SpringBoot211ReleaseZhongwenWendang/img/fullscreen.png
SpringBoot211ReleaseZhongwenWendang/img/loader.gif
SpringBoot211ReleaseZhongwenWendang/img/menu-icon.png
SpringBoot211ReleaseZhongwenWendang/img/save.png
SpringBoot211ReleaseZhongwenWendang/img/saved.png
SpringBoot211ReleaseZhongwenWendang/img/settings-s.png
SpringBoot211ReleaseZhongwenWendang/img/settings.png
SpringBoot211ReleaseZhongwenWendang/img/star.png
SpringBoot211ReleaseZhongwenWendang/js/__init__.py
SpringBoot211ReleaseZhongwenWendang/js/epub.js
SpringBoot211ReleaseZhongwenWendang/js/epub.min.js
SpringBoot211ReleaseZhongwenWendang/js/epub.min.map
SpringBoot211ReleaseZhongwenWendang/js/hooks.min.js
SpringBoot211ReleaseZhongwenWendang/js/hooks.min.map
SpringBoot211ReleaseZhongwenWendang/js/reader.js
SpringBoot211ReleaseZhongwenWendang/js/reader.js.map
SpringBoot211ReleaseZhongwenWendang/js/reader.min.js
spring_boot_2_1_1_release_zhongwen_wendang-2024.3.5.0.dist-info/METADATA
spring_boot_2_1_1_release_zhongwen_wendang-2024.3.5.0.dist-info/WHEEL
spring_boot_2_1_1_release_zhongwen_wendang-2024.3.5.0.dist-info/entry_points.txt
spring_boot_2_1_1_release_zhongwen_wendang-2024.3.5.0.dist-info/top_level.txt
spring_boot_2_1_1_release_zhongwen_wendang-2024.3.5.0.dist-info/RECORD
